pydlmafs/__init__.py
pydlmafs/calc.py
pydlmafs/helpers.py
pydlmafs/linalg.py
pydlmafs/probstat.py
pydlmafs-0.0.4.dist-info/LICENSE
pydlmafs-0.0.4.dist-info/METADATA
pydlmafs-0.0.4.dist-info/WHEEL
pydlmafs-0.0.4.dist-info/top_level.txt
pydlmafs-0.0.4.dist-info/RECORD
