Metadata-Version: 2.1
Name: pydlmafs
Version: 0.0.4
Summary: Python basic Deep Learning maths package
Home-page: https://github.com/booleangabs/pydlmafs
Author: José Gabriel Pereira Tavares
Author-email: jgpt@cin.ufpe.br
License: MIT
Download-URL: https://github.com/booleangabs/pydlmafs/releases/download/v001/pydlmafs-0.0.1.tar.gz
Keywords: math,deeplearning,python3
Platform: UNKNOWN
Classifier: Programming Language :: Python :: 3
Classifier: License :: OSI Approved :: MIT License
Classifier: Operating System :: OS Independent
Requires-Python: >=3.6
Requires-Dist: matplotlib
